read_ad.py
read_ad-1.0.0.dist-info/LICENSE
read_ad-1.0.0.dist-info/METADATA
read_ad-1.0.0.dist-info/WHEEL
read_ad-1.0.0.dist-info/top_level.txt
read_ad-1.0.0.dist-info/RECORD
