Metadata-Version: 2.1
Name: read-ad
Version: 1.0.0
Summary: COM-based readonly access for Active Directory in Python 3
Home-page: https://github.com/blackstream-x/python-read-ad
Author: Rainer Schwarzbach
Author-email: rainer@blackstream.de
License: MIT
Project-URL: Source, https://github.com/blackstream-x/python-read-ad
Project-URL: Tracker, https://github.com/blackstream-x/python-read-ad/issues
Platform: win32
Classifier: Development Status :: 5 - Production/Stable
Classifier: Intended Audience :: Developers
Classifier: Topic :: Software Development :: Libraries
Classifier: License :: OSI Approved :: MIT License
Classifier: Operating System :: Microsoft :: Windows
Classifier: Programming Language :: Python :: 3
Classifier: Programming Language :: Python :: 3.6
Classifier: Programming Language :: Python :: 3.7
Classifier: Programming Language :: Python :: 3.8
Classifier: Programming Language :: Python :: 3.9
Classifier: Programming Language :: Python :: 3 :: Only
Requires-Python: >=3.6
Requires-Dist: pywin32
